[
    {
        "accuracy": "55.33%",
        "average_bleu_score": 0.00771845063125037,
        "agent_histogram": {
            "cognition": 23,
            "anchoring": 47,
            "associate": 48,
            "logician": 25,
            "cot": 7
        },
        "epochs": 10,
        "learning_rate": 0.01,
        "loss_function": "MSELoss",
        "hidden_sizes": [
            128,
            64
        ]
    },
    {
        "accuracy": "55.33%",
        "average_bleu_score": 0.00771845063125037,
        "agent_histogram": {
            "cognition": 23,
            "anchoring": 47,
            "associate": 48,
            "logician": 25,
            "cot": 7
        },
        "epochs": 10,
        "learning_rate": 0.001,
        "loss_function": "MSELoss",
        "hidden_sizes": [
            128,
            64
        ]
    },
    {
        "accuracy": "55.33%",
        "average_bleu_score": 0.007710445651068163,
        "agent_histogram": {
            "cognition": 22,
            "anchoring": 47,
            "associate": 49,
            "logician": 25,
            "cot": 7
        },
        "epochs": 10,
        "learning_rate": 0.001,
        "loss_function": "CrossEntropyLoss",
        "hidden_sizes": [
            128,
            64
        ]
    },
    {
        "accuracy": "55.33%",
        "average_bleu_score": 0.007710445651068163,
        "agent_histogram": {
            "cognition": 22,
            "anchoring": 47,
            "associate": 49,
            "logician": 25,
            "cot": 7
        },
        "epochs": 15,
        "learning_rate": 0.001,
        "loss_function": "CrossEntropyLoss",
        "hidden_sizes": [
            128,
            64
        ]
    },
    {
        "accuracy": "55.33%",
        "average_bleu_score": 0.007710445651068163,
        "agent_histogram": {
            "cognition": 22,
            "anchoring": 47,
            "associate": 49,
            "logician": 25,
            "cot": 7
        },
        "epochs": 10,
        "learning_rate": 0.001,
        "loss_function": "CrossEntropyLoss",
        "hidden_sizes": [
            128,
            64
        ],
        "optimizer": "AdamW"
    },
    {
        "accuracy": "54.67%",
        "average_bleu_score": 0.007697597728272531,
        "agent_histogram": {
            "cognition": 22,
            "anchoring": 47,
            "associate": 48,
            "logician": 26,
            "cot": 7
        },
        "epochs": 10,
        "learning_rate": 0.001,
        "loss_function": "MSELoss",
        "hidden_sizes": [
            128,
            64
        ],
        "optimizer": "AdamW"
    },
    {
        "accuracy": "55.33%",
        "average_bleu_score": 0.00771845063125037,
        "agent_histogram": {
            "cognition": 23,
            "anchoring": 47,
            "associate": 48,
            "logician": 25,
            "cot": 7
        },
        "epochs": 15,
        "learning_rate": 0.001,
        "loss_function": "MSELoss",
        "hidden_sizes": [
            128,
            64
        ],
        "optimizer": "AdamW"
    },
    {
        "accuracy": "55.33%",
        "average_bleu_score": 0.00771845063125037,
        "agent_histogram": {
            "cognition": 23,
            "anchoring": 47,
            "associate": 48,
            "logician": 25,
            "cot": 7
        },
        "epochs": 15,
        "learning_rate": 0.001,
        "loss_function": "MSELoss",
        "hidden_sizes": [
            128,
            64
        ],
        "optimizer": "AdamW"
    }
]