{
    "id": 446,
    "question": "Who was expelled from the Surrealist movement due to his views on the Spanish Civil War?",
    "true_answer": [
        "Dal\u00edesque",
        "Dal\u00ed",
        "Dal\u00ed",
        "Salvador Domingo Felipe Jacinto Dal\u00ed i Domenech",
        "Salvador Domingo Felipe Jacinto Dal\u00ed i Dom\u00e8nech, 1st Marquis of P\u00fabol",
        "Salvador Dal\u00ed",
        "Salvador Dal\u00ed",
        "Salvador Dali",
        "Salvador Domingo Felipe Jacinto Dal\u00ed i Dom\u00e8nech",
        "Avida Dollars",
        "salvador dali i domenech",
        "Salvidor Dali",
        "salvador felip jacint dali domenech",
        "dal\u00ed",
        "Salvador Domingo Felipe Jacinto Dali i Domenech",
        "Salvador Domingo Felipe Jacinto Dali i Dom\u00e8nech",
        "salvador domingo felipe jacinto dali i dom\u00e8nech",
        "nuclear cross",
        "salvador domenec felip jacint dal\u00ed domenech",
        "meanings of paintings by salvador dali",
        "salvador domingo felipe jacinto dal\u00ed i domenech",
        "Dali salvador",
        "Salvador Felipe Jacinto Dali i Domenech",
        "Salvador Felip Jacint Dali Domenech",
        "salvador felipe jacinto dali",
        "Salvador dali",
        "The Meanings of the Paintings of Salvador Dali",
        "salvador dal\u00ec",
        "Nuclear cross",
        "marques de pubol",
        "salvador felipe jacinto dali i domenech",
        "salvador dali",
        "Meanings of Paintings by Salvador Dali",
        "Salvador dhali",
        "salvador felip jacint dal\u00ed dom\u00e8nech",
        "salvidor dali",
        "dali salvador",
        "salvador domingo felipe jacinto dal\u00ed i dom\u00e8nech 1st marquis of p\u00fabol",
        "Salvador Felip Jacint Dal\u00ed Dom\u00e8nech",
        "Salvador Dal\u00ed i Dom\u00e8nech",
        "Salvador Dal\u00ec",
        "salvador dal\u00ed i dom\u00e8nech",
        "dali lithograph",
        "Salvador Domenec Felip Jacint Dali Domenech",
        "Salvador Felipe Jacinto Dali",
        "salvador domingo felipe jacinto dali i domenech",
        "salvador domingo felipe jacinto dal\u00ed i dom\u00e8nech",
        "Salvador dal\u00ec",
        "daliesque",
        "Salvadore Dali",
        "Marques de Pubol",
        "Dali Lithograph",
        "salvador dhali",
        "dal\u00edesque",
        "salvador domenec felip jacint dali domenech",
        "avida dollars",
        "Salvador Dali i Domenech",
        "Salvador Domenec Felip Jacint Dal\u00ed Domenech",
        "Daliesque",
        "salvador felipe jacinto dala",
        "salvadore dali",
        "Salvador Felipe Jacinto DalA",
        "meanings of paintings of salvador dali",
        "salvador dal\u00ed"
    ],
    "cot": {
        "cot_input": "\n        To solve the problem, Please think and reason step by step, then answer.\n        question:\n        Who was expelled from the Surrealist movement due to his views on the Spanish Civil War?\n        \n        Generation Format:\n        Reasoning process:\n        Answer:\n                    ",
        "cot_output": "Reasoning process:\n1. The Surrealist movement was a group of artists and writers who sought to channel the unconscious as a means to unlock the power of the imagination.\n2. The Spanish Civil War took place from 1936 to 1939, and it was a conflict between the Republicans, who were loyal to the democratic, left-leaning Second Spanish Republic, and the Nationalists, a rebel group led by General Francisco Franco.\n3. Some members of the Surrealist movement, including Andre Breton, supported the Republican side in the Spanish Civil War, while others, such as Salvador Dali, expressed support for the Nationalists.\n4. Salvador Dali's support for the Nationalists and his refusal to denounce Franco led to his expulsion from the Surrealist movement.\nAnswer: Salvador Dali",
        "cot_correctness": "True"
    },
    "anchoring": {
        "anchoring_input": "\n        Here is an answer generated by a language model with the reasoning process.\n        question:\n        Who was expelled from the Surrealist movement due to his views on the Spanish Civil War?\n        answer:\n        Reasoning process:\n1. The Surrealist movement was a group of artists and writers who sought to channel the unconscious as a means to unlock the power of the imagination.\n2. The Spanish Civil War took place from 1936 to 1939, and it was a conflict between the Republicans, who were loyal to the democratic, left-leaning Second Spanish Republic, and the Nationalists, a rebel group led by General Francisco Franco.\n3. Some members of the Surrealist movement, including Andre Breton, supported the Republican side in the Spanish Civil War, while others, such as Salvador Dali, expressed support for the Nationalists.\n4. Salvador Dali's support for the Nationalists and his refusal to denounce Franco led to his expulsion from the Surrealist movement.\nAnswer: Salvador DaliTo provide the language model with relevant background and anchoring knowledge and concepts, helping it better understand the question.\n        I retrieved some knowledge that is may unfamiliar with the model: \n        knowledge:\n        The content that may be unfamiliar to the model includes:\n- The involvement of the Mexican Communist Party and the founding of the Liga Espartaquista and the Partido Popular Socialista by an individual who was later expelled for questioning and criticizing the errors of the left.\n- The impact of the Spanish Civil War on individuals and political organizations, leading to resignations, expulsions, and shifts in ideological positions.\n- The division and neutrality of the French government during the Spanish Civil War, and the internal and external pressures that influenced their decision-making.\n\nAnalyzing the role of these contents:\n- The involvement in the Mexican Communist Party and the subsequent founding and expulsion from other political organizations demonstrates the complex and shifting nature of political alliances and ideologies during this time period. It also highlights the internal conflicts and criticisms within leftist movements.\n- The impact of the Spanish Civil War on individuals and political organizations reflects the broader international implications of the conflict, as well as the ethical and ideological dilemmas faced by pacifists and political leaders.\n- The division and neutrality of the French government during the Spanish Civil War illustrates the complex geopolitical considerations and domestic pressures that influenced their decision-making, shedding light on the broader context of international involvement in the conflict.\n        Please verify the above reasoning process for errors, \n        then enhance this reasoning process using retrieved knowledge to help it better understand the question,\n        Afterward, give the answer based on the enhanced reasoning process.\n        \n        Generation Format:\n        knowledge enhanced inference process:\n        Answer:\n                    ",
        "anchoring_output": "Enhanced reasoning process with retrieved knowledge:\n\n1. The Surrealist movement was a group of artists and writers who sought to channel the unconscious as a means to unlock the power of the imagination. The movement had members with diverse political views and affiliations.\n\n2. The Spanish Civil War took place from 1936 to 1939, and it was a conflict between the Republicans, who were loyal to the democratic, left-leaning Second Spanish Republic, and the Nationalists, a rebel group led by General Francisco Franco. The war attracted international attention and involvement, with various political and ideological factions taking sides.\n\n3. Some members of the Surrealist movement, including Andre Breton, supported the Republican side in the Spanish Civil War, while others, such as Salvador Dali, expressed support for the Nationalists. This division within the Surrealist movement led to internal conflicts and debates about the role of art and politics.\n\n4. Additionally, the involvement of the Mexican Communist Party and the founding of the Liga Espartaquista and the Partido Popular Socialista by an individual who was later expelled for questioning and criticizing the errors of the left, demonstrates the complex and shifting nature of political alliances and ideologies during this time period. It also highlights the internal conflicts and criticisms within leftist movements, which may have influenced the dynamics within the Surrealist movement.\n\n5. Salvador Dali's support for the Nationalists and his refusal to denounce Franco led to his expulsion from the Surrealist movement. This expulsion reflects the broader impact of the Spanish Civil War on individuals and political organizations, leading to resignations, expulsions, and shifts in ideological positions.\n\nAnswer:\nSalvador Dali was expelled from the Surrealist movement due to his views on the Spanish Civil War, particularly his support for the Nationalists and his refusal to denounce Franco.",
        "anchoring_correctness": "True"
    },
    "associate": {
        "associate_input": "\n        Here is an answer generated by a language model with the reasoning process.\n        question:\n        Who was expelled from the Surrealist movement due to his views on the Spanish Civil War?\n        answer:\n        Reasoning process:\n1. The Surrealist movement was a group of artists and writers who sought to channel the unconscious as a means to unlock the power of the imagination.\n2. The Spanish Civil War took place from 1936 to 1939, and it was a conflict between the Republicans, who were loyal to the democratic, left-leaning Second Spanish Republic, and the Nationalists, a rebel group led by General Francisco Franco.\n3. Some members of the Surrealist movement, including Andre Breton, supported the Republican side in the Spanish Civil War, while others, such as Salvador Dali, expressed support for the Nationalists.\n4. Salvador Dali's support for the Nationalists and his refusal to denounce Franco led to his expulsion from the Surrealist movement.\nAnswer: Salvador Dali\n        To deepen the language model's understanding of the question through familiarity with basic and advanced pieces of information.\n        Encourage the language model to comprehend the question more thoroughly and expand its knowledge boundaries.\n        I retrieved some associateal knowledge that is familiar to the model or advanced information beyond the language model's already familiar associateal knowledge from these passages. \n        knowledge:\n        The passages provided contain information about various individuals and their views on the Spanish Civil War. One individual, who was expelled from the Surrealist movement due to his views on the Spanish Civil War, is not explicitly mentioned in the provided passages. However, the passages do provide insight into the broader context of the Spanish Civil War and the diverse range of opinions and actions taken by individuals and political organizations during that time.\n\nThe passages mention individuals who were expelled from political parties for criticizing bureaucratic practices, individuals who supported the cause of the Republic during the Spanish Civil War, and individuals who adopted a policy of neutrality or non-intervention. These diverse perspectives and actions reflect the complex and divisive nature of the Spanish Civil War, which deeply divided not only Spain but also had implications for other countries and political movements.\n\nThe information provided in the passages can deepen the model's understanding of the historical and political context surrounding the Spanish Civil War, as well as the various ideological and strategic considerations that influenced individuals and political organizations during that time. This deeper understanding can help the model to appreciate the complexities of the situation and the potential impact of differing views on the course of history.\n        Please verify the above reasoning process for errors, \n        then enhance this reasoning process using retrieved knowledge to deepen the understanding of the question through familiarity with basic and advanced pieces of information,\n        comprehend the question more thoroughly, and expand the knowledge boundaries.\n        Afterward, give the answer based on the enhanced reasoning process.\n        \n        Generation Format:\n        knowledge enhanced inference process:\n        Answer:\n                    ",
        "associate_output": "The reasoning process provided is accurate and provides a good understanding of the context surrounding the Spanish Civil War and its impact on the Surrealist movement. To enhance the reasoning process, we can further delve into the specific events that led to the expulsion of Salvador Dali from the Surrealist movement.\n\nSalvador Dali, a prominent member of the Surrealist movement, expressed support for the Nationalist side in the Spanish Civil War and refused to denounce General Francisco Franco. This stance was in direct opposition to the views of other Surrealists, such as Andre Breton, who supported the Republican side. Dali's public support for the Nationalists and his refusal to align with the majority of the Surrealist movement led to his expulsion from the group.\n\nThis deeper understanding of the specific actions and positions taken by Salvador Dali within the context of the Spanish Civil War and the Surrealist movement provides a more comprehensive view of the events that led to his expulsion.\n\nAnswer: Salvador Dali",
        "associate_correctness": "True"
    },
    "logician": {
        "logician_input": "\n        Here is an answer generated by a language model with the reasoning process.\n        question:\n        Who was expelled from the Surrealist movement due to his views on the Spanish Civil War?\n        answer:\n        Reasoning process:\n1. The Surrealist movement was a group of artists and writers who sought to channel the unconscious as a means to unlock the power of the imagination.\n2. The Spanish Civil War took place from 1936 to 1939, and it was a conflict between the Republicans, who were loyal to the democratic, left-leaning Second Spanish Republic, and the Nationalists, a rebel group led by General Francisco Franco.\n3. Some members of the Surrealist movement, including Andre Breton, supported the Republican side in the Spanish Civil War, while others, such as Salvador Dali, expressed support for the Nationalists.\n4. Salvador Dali's support for the Nationalists and his refusal to denounce Franco led to his expulsion from the Surrealist movement.\nAnswer: Salvador Dali\n        To improve the language model's causal reasoning and logical inference capabilities.\n        I retrieved some knowledge that can help enhance the language model's causal reasoning and logical inference abilities.\n        knowledge:\n        The selected passages provide information about individuals and organizations being expelled or resigning from their respective groups due to their views on the Spanish Civil War. This information can help enhance the model's causal reasoning and logical inference abilities by providing examples of real-world consequences of holding certain beliefs or expressing certain opinions.\n\nBy analyzing these passages, the model can learn that expressing dissenting views or criticizing the actions of certain organizations or governments can lead to expulsion or resignation. This can help the model understand the potential consequences of holding certain beliefs or speaking out against established norms or policies.\n\nAdditionally, the passages provide insights into the complex political dynamics surrounding the Spanish Civil War, including the involvement of various political ideologies such as communism, socialism, and pacifism. This can help the model develop a deeper understanding of the historical context and the interconnectedness of different political movements and their actions.\n\nOverall, the selected information can impact the improvement of the model's causal reasoning and logical inference capabilities by providing real-world examples of the consequences of expressing dissenting views and by deepening its understanding of the complex political dynamics surrounding historical events.\n        Please verify the above reasoning process for errors, \n        then enhance this reasoning process using retrieved knowledge to enhance the causal reasoning and logical inference abilities.\n        Afterward, give the answer based on the enhanced reasoning process.\n        \n        Generation Format:\n        knowledge enhanced inference process:\n        Answer:\n                    ",
        "logician_output": "knowledge enhanced reasoning process:\n1. The Surrealist movement was a group of artists and writers who sought to channel the unconscious as a means to unlock the power of the imagination, and it was also politically active, with members expressing support for various political causes.\n2. The Spanish Civil War took place from 1936 to 1939, and it was a conflict between the Republicans, who were loyal to the democratic, left-leaning Second Spanish Republic, and the Nationalists, a rebel group led by General Francisco Franco. The war attracted international attention and involvement, with various political ideologies and movements taking sides.\n3. Some members of the Surrealist movement, including Andre Breton, supported the Republican side in the Spanish Civil War, aligning themselves with leftist and anti-fascist ideologies.\n4. Salvador Dali, on the other hand, expressed support for the Nationalists and General Franco, which put him at odds with the majority of the Surrealist movement. His refusal to denounce Franco and his political views led to his expulsion from the Surrealist group, as his stance contradicted the anti-fascist and leftist leanings of the movement.\n5. This expulsion serves as an example of the real-world consequences of holding political views that are contrary to those of the group or organization one is associated with, highlighting the interconnectedness of political beliefs and group dynamics.\n\nAnswer: Salvador Dali",
        "logician_correctness": "True"
    },
    "cognition": {
        "cognition_input": "\n        Here is an answer generated by a language model with the reasoning process.\n        question:\n        Who was expelled from the Surrealist movement due to his views on the Spanish Civil War?\n        answer:\n        Reasoning process:\n1. The Surrealist movement was a group of artists and writers who sought to channel the unconscious as a means to unlock the power of the imagination.\n2. The Spanish Civil War took place from 1936 to 1939, and it was a conflict between the Republicans, who were loyal to the democratic, left-leaning Second Spanish Republic, and the Nationalists, a rebel group led by General Francisco Franco.\n3. Some members of the Surrealist movement, including Andre Breton, supported the Republican side in the Spanish Civil War, while others, such as Salvador Dali, expressed support for the Nationalists.\n4. Salvador Dali's support for the Nationalists and his refusal to denounce Franco led to his expulsion from the Surrealist movement.\nAnswer: Salvador Dali\n        To update the language model's knowledge and prevent factual errors, alleviating model illusions. \n        I retrieved some knowledge that may update the language model's knowledge and prevent factual errors, alleviating model illusions\n        Note that these passages are retrieved from the most authoritative knowledge repositories, so they are assumed to be correct.\n        knowledge:\n        The passages do not contain any information related to the expulsion of a person from the Surrealist movement due to their views on the Spanish Civil War. Therefore, the model's existing knowledge on this topic is not contradicted by the provided passages. However, to update the model's knowledge and prevent factual errors, it would be beneficial to provide information specifically related to the expulsion from the Surrealist movement in connection to the Spanish Civil War. This could include details about the individual involved, their views on the war, and the circumstances surrounding their expulsion.\n        Please verify the above reasoning process for errors, \n        then enhance this reasoning process using retrieved knowledge to update the language model's knowledge, prevent factual errors and alleviate model illusions.\n        Afterward, give the answer based on the enhanced reasoning process.\n        \n        Generation Format:\n        knowledge enhanced inference process:\n        Answer:\n                    ",
        "cognition_output": "knowledge enhanced reasoning process:\n1. The Surrealist movement was a group of artists and writers who sought to channel the unconscious as a means to unlock the power of the imagination.\n2. The Spanish Civil War took place from 1936 to 1939, and it was a conflict between the Republicans, who were loyal to the democratic, left-leaning Second Spanish Republic, and the Nationalists, a rebel group led by General Francisco Franco.\n3. Andre Breton, a prominent leader of the Surrealist movement, was a vocal supporter of the Republican side in the Spanish Civil War and advocated for the movement to align with leftist political causes.\n4. Salvador Dali, a member of the Surrealist movement, expressed support for the Nationalists and refused to denounce Franco, which led to tensions within the movement.\n5. Due to his divergent political views and refusal to align with the movement's stance on the Spanish Civil War, Salvador Dali was eventually expelled from the Surrealist movement.\n\nAnswer: Salvador Dali",
        "cognition_correctness": "True"
    }
}